Metadata-Version: 2.1
Name: aipn-guass
Version: 0.1
Summary: Gaussian distributions
Author: Siva Shankar
Author-email: sivarvs11@gmail.com
